jupyter_marimo_proxy/__init__.py
jupyter_marimo_proxy/icon.svg
jupyter_marimo_proxy-0.0.4.dist-info/LICENSE
jupyter_marimo_proxy-0.0.4.dist-info/METADATA
jupyter_marimo_proxy-0.0.4.dist-info/WHEEL
jupyter_marimo_proxy-0.0.4.dist-info/entry_points.txt
jupyter_marimo_proxy-0.0.4.dist-info/top_level.txt
jupyter_marimo_proxy-0.0.4.dist-info/RECORD
